OptionQuant/__init__.py
OptionQuant/option.py
OptionQuant/plotter.py
OptionQuant/pricer.py
OptionQuant/strategy.py
OptionQuant-1.0.0.dist-info/LICENSE
OptionQuant-1.0.0.dist-info/METADATA
OptionQuant-1.0.0.dist-info/WHEEL
OptionQuant-1.0.0.dist-info/top_level.txt
OptionQuant-1.0.0.dist-info/RECORD
