Metadata-Version: 2.1
Name: OptionQuant
Version: 1.0.0
Summary: A package for options trading strategies and analysis
Home-page: https://github.com/sidnand/OptionQuant
Author: Siddharth Nand
Author-email: snand233@gmail.com
Classifier: Programming Language :: Python :: 3
Classifier: License :: OSI Approved :: MIT License
Classifier: Operating System :: OS Independent
Requires-Python: >=3.13
License-File: LICENSE
Requires-Dist: numpy
Requires-Dist: matplotlib
Requires-Dist: quantlib
